ytcc/__init__.py
ytcc/cli.py
ytcc/config.py
ytcc/core.py
ytcc/database.py
ytcc/exceptions.py
ytcc/migration.py
ytcc/printer.py
ytcc/terminal.py
ytcc/tui.py
ytcc/updater.py
ytcc/utils.py
ytcc-2.8.0.data/scripts/ytccf.sh
ytcc-2.8.0.dist-info/METADATA
ytcc-2.8.0.dist-info/WHEEL
ytcc-2.8.0.dist-info/entry_points.txt
ytcc-2.8.0.dist-info/licenses/COPYING
ytcc-2.8.0.dist-info/RECORD
