Metadata-Version: 2.4
Name: ytcc
Version: 2.8.0
Summary: Command line tool to keep track of your favorite playlists
Project-URL: Homepage, https://github.com/woefe/ytcc
Project-URL: Issues, https://github.com/woefe/ytcc/issues
Project-URL: Repository, https://github.com/woefe/ytcc.git
Author-email: Wolfgang Popp <mail@wolfgang-popp.de>
License-Expression: GPL-3.0-or-later
License-File: COPYING
Classifier: Development Status :: 5 - Production/Stable
Classifier: Environment :: Console
Classifier: Intended Audience :: End Users/Desktop
Classifier: License :: OSI Approved :: GNU General Public License v3 or later (GPLv3+)
Classifier: Operating System :: OS Independent
Classifier: Programming Language :: Python :: 3 :: Only
Classifier: Programming Language :: Python :: 3.10
Classifier: Programming Language :: Python :: 3.11
Classifier: Programming Language :: Python :: 3.12
Classifier: Programming Language :: Python :: 3.13
Classifier: Topic :: Multimedia :: Sound/Audio
Classifier: Topic :: Multimedia :: Video
Requires-Python: <4,>=3.10
Requires-Dist: click==8.2.0
Requires-Dist: defusedxml
Requires-Dist: wcwidth
Requires-Dist: yt-dlp
Provides-Extra: youtube-dl
Requires-Dist: youtube-dl; extra == 'youtube-dl'
